{
  "parent": "minecraft:recipes/root",
  "rewards": {
    "recipes": [
      "dinosexpansion:basic_energy_cable"
    ]
  },
  "criteria": {
    "hasItem": {
      "trigger": "minecraft:inventory_changed",
      "conditions": {
        "items": [
          {
            "tag": "minecraft:wool"
          }
        ]
      }
    },
    "has_the_recipe": {
      "trigger": "minecraft:recipe_unlocked",
      "conditions": {
        "recipe": "dinosexpansion:basic_energy_cable"
      }
    }
  },
  "requirements": [
    [
      "hasItem",
      "has_the_recipe"
    ]
  ]
}